{
"type": "FeatureCollection",
"crs": { "type": "name", "properties": { "name": "urn:ogc:def:crs:OGC:1.3:CRS84" } },
                                                                                
"features": [
{ "type": "Feature", "properties": { "事故種別": 1, "発生日": "平成27年2月25日（水）", "発生時間": "午前10時35分ころ", "場所": "品川区小山台１丁目", "路線": "区道", "事故当事者": "自転車（80代男性・死亡）、普通貨物車（70代男性）" }, "geometry": { "type": "Point", "coordinates": [ 139.705922713833701, 35.621364353702262 ] } },
{ "type": "Feature", "properties": { "事故種別": 1, "発生日": "平成27年1月25日（日）", "発生時間": "午前1時13分ころ", "場所": "品川区中延６丁目", "路線": "国道1号", "事故当事者": "歩行者（50代男性・死亡）、タクシー（50代男性）" }, "geometry": { "type": "Point", "coordinates": [ 139.713040809131968, 35.602645315024709 ] } }
]
}
